post_install.py
pycryptexe-1.1.6.dist-info/METADATA
pycryptexe-1.1.6.dist-info/WHEEL
pycryptexe-1.1.6.dist-info/entry_points.txt
pycryptexe-1.1.6.dist-info/top_level.txt
pycryptexe-1.1.6.dist-info/RECORD
